arianna_first_package/__init__.py
arianna_first_package/arianna_first_package.py
arianna_first_package/sub_package_1/__init__.py
arianna_first_package/sub_package_1/my_class_1.py
arianna_first_package/sub_package_2/__init__.py
arianna_first_package/sub_package_2/my_class_2.py
arianna_first_package/sub_package_2/my_class_3.py
arianna_first_package/sub_package_3/__init__.py
arianna_first_package/sub_package_3/my_class_4.py
arianna_first_package-0.2.0.dist-info/AUTHORS.md
arianna_first_package-0.2.0.dist-info/LICENSE
arianna_first_package-0.2.0.dist-info/METADATA
arianna_first_package-0.2.0.dist-info/WHEEL
arianna_first_package-0.2.0.dist-info/RECORD
