Metadata-Version: 2.1
Name: arianna-first-package
Version: 0.2.0
Summary: Arianna's first package is a simple Python package for learning puropses.
Home-page: https://github.com/AriannaBonazza/arianna-first-package
Author: Arianna Bonazza
Author-email: ariannabonazza28@gmail.com
Requires-Python: >=3.10,<4.0
Classifier: Programming Language :: Python :: 3
Classifier: Programming Language :: Python :: 3.10
Classifier: Programming Language :: Python :: 3.11
Classifier: Programming Language :: Python :: 3.12
Classifier: Programming Language :: Python :: 3.13
Project-URL: Documentation, https://AriannaBonazza.github.io/arianna-first-package
Project-URL: Repository, https://github.com/AriannaBonazza/arianna-first-package
